data_components/Category_dropdown.py
data_components/Insert_values.py
data_components/Property_dropdown.py
data_components/__init__.py
data_components/property_dropdown_thread.py
ui_components/__init__.py
ui_components/dropdown.py
ui_components/error_msg.py
ui_components/excel_file_upload.py
ui_components/searchable_dropdown.py
ui_components/uid_table.py
tigl_uid_generator-0.2.2.dist-info/METADATA
tigl_uid_generator-0.2.2.dist-info/WHEEL
tigl_uid_generator-0.2.2.dist-info/top_level.txt
tigl_uid_generator-0.2.2.dist-info/RECORD
